pynamasha/__init__.py
pynamasha/exceptions.py
pynamasha/main.py
pynamasha/scraper.py
pynamasha-1.0.0.dist-info/LICENSE.txt
pynamasha-1.0.0.dist-info/METADATA
pynamasha-1.0.0.dist-info/WHEEL
pynamasha-1.0.0.dist-info/top_level.txt
pynamasha-1.0.0.dist-info/RECORD
