Metadata-Version: 2.1
Name: pynamasha
Version: 1.0.0
Summary: A small example package
Home-page: https://github.com/saeedniksaz/pynamasha
Author: saeedniksaz
Author-email: niksazsaeed@gmail.com
License: UNKNOWN
Platform: UNKNOWN
Classifier: Programming Language :: Python :: 3
Classifier: License :: OSI Approved :: MIT License
Classifier: Operating System :: OS Independent
Requires-Python: >=3.6
License-File: LICENSE.txt
Requires-Dist: requests
Requires-Dist: beautifulsoup4
